LICENSE
MANIFEST.in
README.md
requirements.txt
setup.py
quantiphyse_fabber/__init__.py
quantiphyse_fabber/_version.py
quantiphyse_fabber/dialogs.py
quantiphyse_fabber/fabber.png
quantiphyse_fabber/fabber.svg
quantiphyse_fabber/option_widgets.py
quantiphyse_fabber/process.py
quantiphyse_fabber/tests.py
quantiphyse_fabber/widget.py
quantiphyse_fabber.egg-info/PKG-INFO
quantiphyse_fabber.egg-info/SOURCES.txt
quantiphyse_fabber.egg-info/dependency_links.txt
quantiphyse_fabber.egg-info/entry_points.txt
quantiphyse_fabber.egg-info/requires.txt
quantiphyse_fabber.egg-info/top_level.txt